README.rst
setup.py
signhash/__init__.py
signhash.egg-info/PKG-INFO
signhash.egg-info/SOURCES.txt
signhash.egg-info/dependency_links.txt
signhash.egg-info/top_level.txt