Metadata-Version: 1.1
Name: signhash
Version: 0.1.0
Summary: SignHash for Python
Home-page: https://github.com/SignHash/signhash-cli
Author: SignHash
Author-email: UNKNOWN
License: UNKNOWN
Platform: UNKNOWN
Classifier: Development Status :: 2 - Pre-Alpha
Classifier: Programming Language :: Python :: 3
Classifier: Programming Language :: Python :: 3.4
Classifier: Programming Language :: Python :: 3.5
